django_lc_utils/__init__.py
django_lc_utils/admin.py
django_lc_utils/api_schema.py
django_lc_utils/apps.py
django_lc_utils/celery.py
django_lc_utils/config/__init__.py
django_lc_utils/config/exceptions.py
django_lc_utils/constants.py
django_lc_utils/converters.py
django_lc_utils/decorators.py
django_lc_utils/encoders.py
django_lc_utils/errors/__init__.py
django_lc_utils/errors/error_codes.json
django_lc_utils/errors/error_handler.py
django_lc_utils/errors/error_manager.py
django_lc_utils/helper.py
django_lc_utils/hijack.py
django_lc_utils/io_utils.py
django_lc_utils/microsoft_graph.py
django_lc_utils/migrations.py
django_lc_utils/mixins.py
django_lc_utils/model_fields.py
django_lc_utils/models.py
django_lc_utils/module_utils.py
django_lc_utils/paginators.py
django_lc_utils/raw_query.py
django_lc_utils/read_replica.py
django_lc_utils/sanitizers.py
django_lc_utils/serializers.py
django_lc_utils/smarty_streets.py
django_lc_utils/static_webpack.py
django_lc_utils/storages.py
django_lc_utils/templatetags/__init__.py
django_lc_utils/templatetags/google_recaptcha.py
django_lc_utils/templatetags/phone.py
django_lc_utils/templatetags/sentry.py
django_lc_utils/templatetags/tenants.py
django_lc_utils/tests/__init__.py
django_lc_utils/tests/factories.py
django_lc_utils/tests/test_api_schema.py
django_lc_utils/tests/test_bytes_io.py
django_lc_utils/tests/test_celery.py
django_lc_utils/tests/test_converters.py
django_lc_utils/tests/test_encoders.py
django_lc_utils/tests/test_errors.py
django_lc_utils/tests/test_helpers.py
django_lc_utils/tests/test_hijack.py
django_lc_utils/tests/test_microsoft_graph.py
django_lc_utils/tests/test_model_fields.py
django_lc_utils/tests/test_module_utils.py
django_lc_utils/tests/test_raw_query.py
django_lc_utils/tests/test_read_replica.py
django_lc_utils/tests/test_smarty_streets.py
django_lc_utils/tests/test_static_webpack.py
django_lc_utils/tests/test_storages.py
django_lc_utils/tests/test_template_tags.py
django_lc_utils-1.2.0.dist-info/LICENSE
django_lc_utils-1.2.0.dist-info/METADATA
django_lc_utils-1.2.0.dist-info/WHEEL
django_lc_utils-1.2.0.dist-info/RECORD
