Metadata-Version: 2.3
Name: django-lc-utils
Version: 1.2.0
Summary: Utilities for Django application
License: BSD-3-Clause
Author: Tejas Bhandari
Author-email: tejas@thesummitgrp.com
Requires-Python: >=3.10.10,<4.0.0
Classifier: License :: OSI Approved :: BSD License
Classifier: Programming Language :: Python :: 3
Classifier: Programming Language :: Python :: 3.11
Classifier: Programming Language :: Python :: 3.12
Classifier: Programming Language :: Python :: 3.13
Requires-Dist: Django (>=3.2.15,<5.0)
Requires-Dist: boto3 (>=1.28.3,<2.0.0)
Requires-Dist: django-autocomplete-light (>=3.11.0,<4.0.0)
Requires-Dist: django-constance[database] (>=3.1.0,<4.0.0)
Requires-Dist: django-error-reporting (>=0.10,<0.11)
Requires-Dist: django-model-utils (>=4.2.0,<5.0.0)
Requires-Dist: django-phonenumber-field (>=7.3.0,<8.0.0)
Requires-Dist: django-storages[boto3] (>=1.14.2,<2.0.0)
Requires-Dist: django-tenants (>=3.6.1,<4.0.0)
Requires-Dist: django-twilio-2fa (>=0.20,<1.0)
Requires-Dist: djangorestframework (>=3.12.4,<4.0.0)
Requires-Dist: drf-spectacular (>=0.27.1,<0.28.0)
Requires-Dist: holidays (>=0.44,<0.45)
Requires-Dist: html-sanitizer (>=2.4,<3.0)
Requires-Dist: inflect (>=7.0.0,<8.0.0)
Requires-Dist: openpyxl (>=3.1.2,<4.0.0)
Requires-Dist: phonenumbers (>=8.13.31,<9.0.0)
Requires-Dist: python-magic (>=0.4.27,<0.5.0)
Requires-Dist: semantic-version (>=2.10.0,<3.0.0)
Requires-Dist: sentry-sdk (>=1.41.0)
Requires-Dist: smartystreets-python-sdk (>=4.14.0,<5.0.0)
Requires-Dist: weasyprint (>=61.2)
Requires-Dist: whitenoise (==6.*)
Project-URL: Homepage, https://github.com/Lenders-Cooperative/django-lc-utils
